[{"name":"escamilla/chipmunk","stars":0},{"name":"cspotcode/hookable-typescript","stars":0},{"name":"legastero/stanza","stars":985},{"name":"cotype/core","stars":4},{"name":"rajveerpurohit/angular","stars":0},{"name":"rajveerpurohit/angular","stars":0},{"name":"menendezpoo/Fragment","stars":1},{"name":"cherow/cherow","stars":1546},{"name":"ConsenSys/asekuro-contracts","stars":1},{"name":"XT-Cheng/brick-travel","stars":0},{"name":"XT-Cheng/brick-travel","stars":0},{"name":"microsoft/staticstaging","stars":24},{"name":"PatrickShaw/byexample","stars":2},{"name":"hawtio/hawtio-kubernetes","stars":25},{"name":"Cellfind/node-console-type-fix","stars":0},{"name":"apicollective/apibuilder-js-generator","stars":1},{"name":"jamesmcnamara/shades","stars":251},{"name":"divisionby0/plitka","stars":0},{"name":"prisma-labs/prisma-binding","stars":422},{"name":"aqeel04/sellor","stars":0},{"name":"Quramy/arlecchino","stars":4},{"name":"aqeel04/sellor","stars":0},{"name":"jrcamilon/Magnus","stars":0},{"name":"Kirk-Wang/1980-BATTLE-CITY","stars":0},{"name":"boenni23/prisma-middleware-Resolve-info","stars":0},{"name":"vega/vega-lite-v2","stars":0},{"name":"jellyr/jellyvscode","stars":0},{"name":"TimCarmanGitHub/React-Apps","stars":0},{"name":"PopMedNet-Team/cnds","stars":0},{"name":"PopMedNet-Team/cnds","stars":0},{"name":"Coopyrightdmin/odata2jdl","stars":0},{"name":"bestsamcn/electron-blog","stars":1},{"name":"ardatan/graphql-toolkit","stars":68},{"name":"lmm0591/FrostbiteEditor","stars":3},{"name":"ruszhov/saleor-shop","stars":0},{"name":"ruszhov/saleor-shop","stars":0},{"name":"sonnhfit/vnrobot","stars":0},{"name":"sonnhfit/vnrobot","stars":0},{"name":"BlakeB254/GraphQL-CodeGenerator","stars":0},{"name":"AEB-labs/cruddl","stars":70},{"name":"evannetwork/dbcp","stars":4},{"name":"dingtalk-templates/typescript-react-simple","stars":2},{"name":"ngxs/store","stars":2445},{"name":"Marcisbee/markup-lint","stars":0},{"name":"etherebum/wifidais","stars":0},{"name":"Esri/hub.js","stars":12},{"name":"ffalt/jamserve","stars":0},{"name":"Kajy/VoxelEngine","stars":0},{"name":"yss14/musicshare","stars":4},{"name":"cre8tiv/prisma-vagrant-mongodb","stars":0},{"name":"jbromand/Angular.js-pull","stars":0},{"name":"gugaopeng/Panda.Docs","stars":0},{"name":"JMArtFIN/angular","stars":0},{"name":"antialize/simple-admin","stars":0},{"name":"jmquigley/trailz","stars":1},{"name":"tensorflow/tfjs","stars":11873},{"name":"tatianahutii/Thread.Net","stars":0},{"name":"youtoofan/ChatbotDash","stars":0},{"name":"NathanGavenski/personal-blockchain-frontend","stars":0},{"name":"streamproject/stream-chrome","stars":4},{"name":"andersfischernielsen/TypeChecker","stars":0},{"name":"okkuso/angular-chat","stars":0},{"name":"justinschuldt/project-map-browser","stars":1},{"name":"ikondrat/connections-visualizer","stars":0},{"name":"Asing1001/movieRater.React","stars":14},{"name":"OscarBarbera/ibexdashboard","stars":0},{"name":"BuildIt-Poland/buddy-app","stars":0},{"name":"PavelDochev/Decentralized-Game-Inventory","stars":0},{"name":"wan2land/safen","stars":21},{"name":"antialize/simple-admin","stars":0},{"name":"Manjuanand021/ls_perfect","stars":0},{"name":"tensorflow/tfjs","stars":11873},{"name":"helloyoucan/hwyg-h5-BFF","stars":0},{"name":"DeathlyPlays/Spectral","stars":6},{"name":"jensnicolay/compilets","stars":0},{"name":"cre8tiv/prisma-vagrant-mongodb","stars":0},{"name":"jensnicolay/compilets","stars":0},{"name":"venn-city/poc-nexus-prisma","stars":1},{"name":"lxb229/C2D","stars":0},{"name":"rakmovistara/flowdatamonit","stars":0},{"name":"y-siabruk/elastic-mastery","stars":1},{"name":"jensnicolay/compilets","stars":0},{"name":"NathanGavenski/personal-blockchain-frontend","stars":0},{"name":"StanLepunK/P5JS_typeScript_webPack","stars":2},{"name":"Shinigami92/star-citizen-trade-market-api","stars":5},{"name":"kwowkiller/ng-ionic","stars":0},{"name":"centeractive/koia","stars":4},{"name":"OscarBarbera/ibexdashboard","stars":0},{"name":"q469672930/game","stars":0},{"name":"wan2land/safen","stars":21},{"name":"uicar/app","stars":1},{"name":"qq52184962/kibana","stars":0},{"name":"johndi9/ng2-web","stars":0},{"name":"nanoofficial/nanoCode","stars":0},{"name":"thrashr888/monkey-typescript","stars":2},{"name":"hodlbank/site-mixer","stars":0},{"name":"abobwhite/ball-and-blockchain-web","stars":0},{"name":"jensnicolay/compilets","stars":0},{"name":"dhyanitha/dynamic-forms","stars":0},{"name":"ThanhHieu0195/api-dev-viralworks","stars":0},{"name":"Pavel-research/raml-js-parser-vocabs","stars":0},{"name":"moeznarsidani/Instagram-like","stars":0},{"name":"ronzeidman/rebirthdbts","stars":2},{"name":"wessberg/TypescriptPackageReassembler","stars":0},{"name":"lxb229/C2D","stars":0},{"name":"tonyfromundefined/serverless-graphql-workshop","stars":65},{"name":"nearprotocol/NEARStudio","stars":37},{"name":"xaviergonz/mobx-keystone","stars":83},{"name":"jensnicolay/compilets","stars":0},{"name":"ThanhHieu0195/api-dev-viralworks","stars":0},{"name":"sami93/Sami_PFE","stars":0},{"name":"Pavel-research/raml-js-parser-vocabs","stars":0},{"name":"el-dav/ep-app","stars":0},{"name":"ConnextProject/connext-chainsaw","stars":1},{"name":"josephat94/TM","stars":0},{"name":"yixiangling/abp-ng-Zorro","stars":104},{"name":"Saadelearner/Salesman-Portal","stars":0},{"name":"DRIVER-EU/avro-typescript-converter","stars":0},{"name":"rseech01/eandbAPI","stars":1},{"name":"copernet/ivybch","stars":0},{"name":"thomasW217/Ionic2-Shopping","stars":0},{"name":"Shinigami92/star-citizen-trade-market-api","stars":5},{"name":"OsvaldoMartini/node_modules_react","stars":0},{"name":"JcluoIvan/e-service-customer","stars":0},{"name":"arakawashinji/info-manager","stars":0},{"name":"liuxinqiong/street-view","stars":0},{"name":"JSMonk/hegel","stars":74},{"name":"Softeq/angular-libs","stars":3},{"name":"diegotrp/ibex-dashboard","stars":0},{"name":"pokemonrpg/monsterrpg","stars":0},{"name":"puncsky/vita-claim-as","stars":2},{"name":"daniel-williams/ng-ux","stars":0},{"name":"daniel-williams/ng-ux","stars":0},{"name":"jensnicolay/compilets","stars":0},{"name":"jollytoad/blockly-type-adventures","stars":0},{"name":"hoodie/guardgen","stars":1},{"name":"graphistry/arrow","stars":28},{"name":"divisionby0/addremoveoperator","stars":0},{"name":"arakawashinji/info-manager","stars":0},{"name":"nanoofficial/nanoCode","stars":0},{"name":"Gear-Framework/vue-typescript-gearui","stars":0},{"name":"pepve/soysk","stars":0},{"name":"ConnextProject/connext-kernle","stars":2},{"name":"Esri/filter-gallery","stars":0},{"name":"RealbindDevTeam/CyG","stars":0},{"name":"RyanCavanaugh/dts-dom","stars":65},{"name":"DRIVER-EU/avro-typescript-converter","stars":0},{"name":"cdstarling/dotfiles","stars":0},{"name":"octhuber/namecheap-api-client","stars":0}]